MANIFEST.in
README.md
setup.py
bin/git-release
git_release/__init__.py
git_release/errors.py
git_release/git_helpers.py
git_release/release.py
git_releaseit.egg-info/PKG-INFO
git_releaseit.egg-info/SOURCES.txt
git_releaseit.egg-info/dependency_links.txt
git_releaseit.egg-info/top_level.txt