Metadata-Version: 1.0
Name: git-releaseit
Version: 0.5
Summary: The git release command for auto-incrementing git tags for releases
Home-page: https://github.com/Authentise/git-release
Author: Scott Lemmon
Author-email: skot.biz@gmail.com
License: UNKNOWN
Platform: UNKNOWN
